asyncmongoengine/__init__.py
asyncmongoengine/connection.py
asyncmongoengine/document.py
asyncmongoengine/index.py
asyncmongoengine-0.0.12.dist-info/METADATA
asyncmongoengine-0.0.12.dist-info/WHEEL
asyncmongoengine-0.0.12.dist-info/licenses/LICENSE
asyncmongoengine-0.0.12.dist-info/RECORD
